bitcoin_tools/__init__.py
bitcoin_tools/conf.py
bitcoin_tools/sample_conf.py
bitcoin_tools/utils.py
bitcoin_tools/wallet.py
bitcoin_tools/analysis/__init__.py
bitcoin_tools/analysis/plots.py
bitcoin_tools/analysis/status/__init__.py
bitcoin_tools/analysis/status/data_dump.py
bitcoin_tools/analysis/status/data_processing.py
bitcoin_tools/analysis/status/dust_fast.py
bitcoin_tools/analysis/status/dust_fast_2.py
bitcoin_tools/analysis/status/kill_at_heigh.py
bitcoin_tools/analysis/status/plots.py
bitcoin_tools/analysis/status/run_analysis.py
bitcoin_tools/analysis/status/run_comparative_analysis.py
bitcoin_tools/analysis/status/run_fork_analysis.py
bitcoin_tools/analysis/status/utils.py
bitcoin_tools/core/__init__.py
bitcoin_tools/core/keys.py
bitcoin_tools/core/script.py
bitcoin_tools/core/transaction.py
python_bitcoin_tools-0.2.3.dist-info/LICENSE
python_bitcoin_tools-0.2.3.dist-info/METADATA
python_bitcoin_tools-0.2.3.dist-info/WHEEL
python_bitcoin_tools-0.2.3.dist-info/top_level.txt
python_bitcoin_tools-0.2.3.dist-info/RECORD
