Metadata-Version: 2.1
Name: python-bitcoin-tools
Version: 0.2.3
Summary: Python library created for teaching and researching purposes.
Home-page: https://github.com/sr-gi/bitcoin_tools
Author: Sergi Delgado-Segura and Cristina Pérez-Solà
Author-email: sdelgado@deic.uab.cat, cperez@deic.uab.cat
License: BSD 3
Keywords: bitcoin,transaction builder,key management,chainstate analysis
Platform: UNKNOWN
Classifier: Development Status :: 4 - Beta
Classifier: Intended Audience :: Education
Classifier: Intended Audience :: Developers
Classifier: Intended Audience :: Science/Research
Classifier: License :: OSI Approved :: BSD License
Classifier: Programming Language :: Python :: 2 :: Only
Requires-Dist: ecdsa
Requires-Dist: python-bitcoinlib
Requires-Dist: base58
Requires-Dist: qrcode
Requires-Dist: Pillow
Requires-Dist: plyvel
Requires-Dist: matplotlib
Requires-Dist: numpy
Requires-Dist: ujson
